sharpaikit/__init__.py
sharpaikit/agent.py
sharpaikit/chain.py
sharpaikit/client.py
sharpaikit/code_interpreter.py
sharpaikit/document_loader.py
sharpaikit/errors.py
sharpaikit/graph.py
sharpaikit/memory.py
sharpaikit/models.py
sharpaikit/observability.py
sharpaikit/optimizer.py
sharpaikit/output_parser.py
sharpaikit/process.py
sharpaikit/prompt.py
sharpaikit/rag.py
sharpaikit/tool.py
sharpaikit/unified_client.py
sharpaikit/_grpc/__init__.py
sharpaikit/_grpc/agent_pb2.py
sharpaikit/_grpc/agent_pb2_grpc.py
sharpaikit/_grpc/sharpaikit_pb2.py
sharpaikit/_grpc/sharpaikit_pb2_grpc.py
sharpaikit-0.3.0.dist-info/METADATA
sharpaikit-0.3.0.dist-info/WHEEL
sharpaikit-0.3.0.dist-info/licenses/LICENSE
sharpaikit-0.3.0.dist-info/RECORD
