Metadata-Version: 2.4
Name: sharpaikit
Version: 0.3.0
Summary: Official Python SDK for SharpAIKit - .NET AI/LLM Toolkit with Agent, Chain, Memory, RAG, Graph, and more
Project-URL: Homepage, https://github.com/dxpython/SharpAIKit
Project-URL: Documentation, https://github.com/dxpython/SharpAIKit
Project-URL: Repository, https://github.com/dxpython/SharpAIKit
Author-email: SharpAIKit Team <info@sharpaikit.dev>
Maintainer: Dustin Dong, Evelyn-Liux
License: MIT
License-File: LICENSE
Keywords: agent,ai,chatgpt,grpc,langchain,llm,machine-learning,openai,sharpai
Classifier: Development Status :: 4 - Beta
Classifier: Intended Audience :: Developers
Classifier: License :: OSI Approved :: MIT License
Classifier: Operating System :: OS Independent
Classifier: Programming Language :: Python :: 3
Classifier: Programming Language :: Python :: 3.8
Classifier: Programming Language :: Python :: 3.9
Classifier: Programming Language :: Python :: 3.10
Classifier: Programming Language :: Python :: 3.11
Classifier: Programming Language :: Python :: 3.12
Classifier: Topic :: Scientific/Engineering :: Artificial Intelligence
Classifier: Topic :: Software Development :: Libraries :: Python Modules
Requires-Python: >=3.8
Requires-Dist: grpcio-tools>=1.60.0
Requires-Dist: grpcio>=1.60.0
Requires-Dist: httpx>=0.24.0
Provides-Extra: dev
Requires-Dist: black>=23.0.0; extra == 'dev'
Requires-Dist: mypy>=1.0.0; extra == 'dev'
Requires-Dist: pytest-asyncio>=0.21.0; extra == 'dev'
Requires-Dist: pytest>=7.0.0; extra == 'dev'
